xacc/pytnqvm.so
xacc/plugins/libtnqvm-itensor.so
xacc/plugins/libtnqvm.so
xacc/lib/libblas.so.3
xacc/lib/libgfortran.so.1
xacc/lib/liblapack.so.3
tnqvm-0.1.9.dist-info/top_level.txt
tnqvm-0.1.9.dist-info/DESCRIPTION.rst
tnqvm-0.1.9.dist-info/METADATA
tnqvm-0.1.9.dist-info/WHEEL
tnqvm-0.1.9.dist-info/RECORD
tnqvm-0.1.9.dist-info/metadata.json
