Metadata-Version: 2.0
Name: tnqvm
Version: 0.1.9
Summary: XACC plugins for interacting with TNQVM
Home-page: UNKNOWN
Author: Alex McCaskey
Author-email: xacc-dev@eclipse.org
License: UNKNOWN
Platform: UNKNOWN
Requires-Dist: xacc (>=0.1.15)
